{"builtWith":"0.15.15","comments":[{"LineComment":" | Similar to `Halogen.HTML as HH` but contains SVG elements."},{"LineComment":" | We recommend importing this module via the `SE` module alias:"},{"LineComment":" | ```"},{"LineComment":" | import Halogen.Svg.Elements as SE"},{"LineComment":" | ```"}],"decls":[{"annotation":{"meta":null,"sourceSpan":{"end":[43,87],"start":[43,1]}},"bindType":"NonRec","expression":{"abstraction":{"annotation":{"meta":{"metaType":"IsForeign"},"sourceSpan":{"end":[44,20],"start":[44,11]}},"type":"Var","value":{"identifier":"elementNS","moduleName":["Halogen","HTML","Elements"]}},"annotation":{"meta":null,"sourceSpan":{"end":[44,61],"start":[44,11]}},"argument":{"abstraction":{"annotation":{"meta":{"metaType":"IsNewtype"},"sourceSpan":{"end":[44,31],"start":[44,22]}},"type":"Var","value":{"identifier":"Namespace","moduleName":["Halogen","VDom","Types"]}},"annotation":{"meta":null,"sourceSpan":{"end":[44,60],"start":[44,22]}},"argument":{"annotation":{"meta":null,"sourceSpan":{"end":[44,60],"start":[44,32]}},"type":"Literal","value":{"literalType":"StringLiteral","value":"http://www.w3.org/2000/svg"}},"type":"App"},"type":"App"},"identifier":"element"},{"annotation":{"meta":null,"sourceSpan":{"end":[58,45],"start":[58,1]}},"bindType":"NonRec","expression":{"annotation":{"meta":null,"sourceSpan":{"end":[58,45],"start":[58,1]}},"argument":"props","body":{"abstraction":{"abstraction":{"abstraction":{"annotation":{"meta":null,"sourceSpan":{"end":[59,24],"start":[59,17]}},"type":"Var","value":{"identifier":"element","moduleName":["Halogen","Svg","Elements"]}},"annotation":{"meta":null,"sourceSpan":{"end":[59,45],"start":[59,17]}},"argument":{"abstraction":{"annotation":{"meta":{"metaType":"IsNewtype"},"sourceSpan":{"end":[59,34],"start":[59,26]}},"type":"Var","value":{"identifier":"ElemName","moduleName":["Halogen","VDom","Types"]}},"annotation":{"meta":null,"sourceSpan":{"end":[59,44],"start":[59,26]}},"argument":{"annotation":{"meta":null,"sourceSpan":{"end":[59,44],"start":[59,35]}},"type":"Literal","value":{"literalType":"StringLiteral","value":"ellipse"}},"type":"App"},"type":"App"},"annotation":{"meta":null,"sourceSpan":{"end":[59,51],"start":[59,17]}},"argument":{"annotation":{"meta":null,"sourceSpan":{"end":[59,51],"start":[59,46]}},"type":"Var","value":{"identifier":"props","sourcePos":[59,1]}},"type":"App"},"annotation":{"meta":null,"sourceSpan":{"end":[59,54],"start":[59,17]}},"argument":{"annotation":{"meta":null,"sourceSpan":{"end":[59,54],"start":[59,52]}},"type":"Literal","value":{"literalType":"ArrayLiteral","value":[]}},"type":"App"},"type":"Abs"},"identifier":"ellipse"},{"annotation":{"meta":null,"sourceSpan":{"end":[85,57],"start":[85,1]}},"bindType":"NonRec","expression":{"abstraction":{"annotation":{"meta":null,"sourceSpan":{"end":[86,24],"start":[86,17]}},"type":"Var","value":{"identifier":"element","moduleName":["Halogen","Svg","Elements"]}},"annotation":{"meta":null,"sourceSpan":{"end":[86,51],"start":[86,17]}},"argument":{"abstraction":{"annotation":{"meta":{"metaType":"IsNewtype"},"sourceSpan":{"end":[86,34],"start":[86,26]}},"type":"Var","value":{"identifier":"ElemName","moduleName":["Halogen","VDom","Types"]}},"annotation":{"meta":null,"sourceSpan":{"end":[86,50],"start":[86,26]}},"argument":{"annotation":{"meta":null,"sourceSpan":{"end":[86,50],"start":[86,35]}},"type":"Literal","value":{"literalType":"StringLiteral","value":"foreignObject"}},"type":"App"},"type":"App"},"identifier":"foreignObject"},{"annotation":{"meta":null,"sourceSpan":{"end":[49,33],"start":[49,1]}},"bindType":"NonRec","expression":{"abstraction":{"annotation":{"meta":null,"sourceSpan":{"end":[50,12],"start":[50,5]}},"type":"Var","value":{"identifier":"element","moduleName":["Halogen","Svg","Elements"]}},"annotation":{"meta":null,"sourceSpan":{"end":[50,27],"start":[50,5]}},"argument":{"abstraction":{"annotation":{"meta":{"metaType":"IsNewtype"},"sourceSpan":{"end":[50,23],"start":[50,15]}},"type":"Var","value":{"identifier":"ElemName","moduleName":["Halogen","VDom","Types"]}},"annotation":{"meta":null,"sourceSpan":{"end":[50,27],"start":[50,15]}},"argument":{"annotation":{"meta":null,"sourceSpan":{"end":[50,27],"start":[50,24]}},"type":"Literal","value":{"literalType":"StringLiteral","value":"g"}},"type":"App"},"type":"App"},"identifier":"g"},{"annotation":{"meta":null,"sourceSpan":{"end":[55,41],"start":[55,1]}},"bindType":"NonRec","expression":{"annotation":{"meta":null,"sourceSpan":{"end":[55,41],"start":[55,1]}},"argument":"props","body":{"abstraction":{"abstraction":{"abstraction":{"annotation":{"meta":null,"sourceSpan":{"end":[56,22],"start":[56,15]}},"type":"Var","value":{"identifier":"element","moduleName":["Halogen","Svg","Elements"]}},"annotation":{"meta":null,"sourceSpan":{"end":[56,41],"start":[56,15]}},"argument":{"abstraction":{"annotation":{"meta":{"metaType":"IsNewtype"},"sourceSpan":{"end":[56,32],"start":[56,24]}},"type":"Var","value":{"identifier":"ElemName","moduleName":["Halogen","VDom","Types"]}},"annotation":{"meta":null,"sourceSpan":{"end":[56,40],"start":[56,24]}},"argument":{"annotation":{"meta":null,"sourceSpan":{"end":[56,40],"start":[56,33]}},"type":"Literal","value":{"literalType":"StringLiteral","value":"image"}},"type":"App"},"type":"App"},"annotation":{"meta":null,"sourceSpan":{"end":[56,47],"start":[56,15]}},"argument":{"annotation":{"meta":null,"sourceSpan":{"end":[56,47],"start":[56,42]}},"type":"Var","value":{"identifier":"props","sourcePos":[56,1]}},"type":"App"},"annotation":{"meta":null,"sourceSpan":{"end":[56,50],"start":[56,15]}},"argument":{"annotation":{"meta":null,"sourceSpan":{"end":[56,50],"start":[56,48]}},"type":"Literal","value":{"literalType":"ArrayLiteral","value":[]}},"type":"App"},"type":"Abs"},"identifier":"image"},{"annotation":{"meta":null,"sourceSpan":{"end":[70,39],"start":[70,1]}},"bindType":"NonRec","expression":{"annotation":{"meta":null,"sourceSpan":{"end":[70,39],"start":[70,1]}},"argument":"props","body":{"abstraction":{"abstraction":{"abstraction":{"annotation":{"meta":null,"sourceSpan":{"end":[71,21],"start":[71,14]}},"type":"Var","value":{"identifier":"element","moduleName":["Halogen","Svg","Elements"]}},"annotation":{"meta":null,"sourceSpan":{"end":[71,39],"start":[71,14]}},"argument":{"abstraction":{"annotation":{"meta":{"metaType":"IsNewtype"},"sourceSpan":{"end":[71,31],"start":[71,23]}},"type":"Var","value":{"identifier":"ElemName","moduleName":["Halogen","VDom","Types"]}},"annotation":{"meta":null,"sourceSpan":{"end":[71,38],"start":[71,23]}},"argument":{"annotation":{"meta":null,"sourceSpan":{"end":[71,38],"start":[71,32]}},"type":"Literal","value":{"literalType":"StringLiteral","value":"line"}},"type":"App"},"type":"App"},"annotation":{"meta":null,"sourceSpan":{"end":[71,45],"start":[71,14]}},"argument":{"annotation":{"meta":null,"sourceSpan":{"end":[71,45],"start":[71,40]}},"type":"Var","value":{"identifier":"props","sourcePos":[71,1]}},"type":"App"},"annotation":{"meta":null,"sourceSpan":{"end":[71,48],"start":[71,14]}},"argument":{"annotation":{"meta":null,"sourceSpan":{"end":[71,48],"start":[71,46]}},"type":"Literal","value":{"literalType":"ArrayLiteral","value":[]}},"type":"App"},"type":"Abs"},"identifier":"line"},{"annotation":{"meta":null,"sourceSpan":{"end":[94,43],"start":[94,1]}},"bindType":"NonRec","expression":{"abstraction":{"annotation":{"meta":null,"sourceSpan":{"end":[95,17],"start":[95,10]}},"type":"Var","value":{"identifier":"element","moduleName":["Halogen","Svg","Elements"]}},"annotation":{"meta":null,"sourceSpan":{"end":[95,37],"start":[95,10]}},"argument":{"abstraction":{"annotation":{"meta":{"metaType":"IsNewtype"},"sourceSpan":{"end":[95,28],"start":[95,20]}},"type":"Var","value":{"identifier":"ElemName","moduleName":["Halogen","VDom","Types"]}},"annotation":{"meta":null,"sourceSpan":{"end":[95,37],"start":[95,20]}},"argument":{"annotation":{"meta":null,"sourceSpan":{"end":[95,37],"start":[95,29]}},"type":"Literal","value":{"literalType":"StringLiteral","value":"marker"}},"type":"App"},"type":"App"},"identifier":"marker"},{"annotation":{"meta":null,"sourceSpan":{"end":[91,36],"start":[91,1]}},"bindType":"NonRec","expression":{"abstraction":{"annotation":{"meta":null,"sourceSpan":{"end":[92,15],"start":[92,8]}},"type":"Var","value":{"identifier":"element","moduleName":["Halogen","Svg","Elements"]}},"annotation":{"meta":null,"sourceSpan":{"end":[92,33],"start":[92,8]}},"argument":{"abstraction":{"annotation":{"meta":{"metaType":"IsNewtype"},"sourceSpan":{"end":[92,26],"start":[92,18]}},"type":"Var","value":{"identifier":"ElemName","moduleName":["Halogen","VDom","Types"]}},"annotation":{"meta":null,"sourceSpan":{"end":[92,33],"start":[92,18]}},"argument":{"annotation":{"meta":null,"sourceSpan":{"end":[92,33],"start":[92,27]}},"type":"Literal","value":{"literalType":"StringLiteral","value":"mask"}},"type":"App"},"type":"App"},"identifier":"mask"},{"annotation":{"meta":null,"sourceSpan":{"end":[111,41],"start":[111,1]}},"bindType":"NonRec","expression":{"annotation":{"meta":null,"sourceSpan":{"end":[111,41],"start":[111,1]}},"argument":"props","body":{"abstraction":{"abstraction":{"abstraction":{"annotation":{"meta":null,"sourceSpan":{"end":[112,22],"start":[112,15]}},"type":"Var","value":{"identifier":"element","moduleName":["Halogen","Svg","Elements"]}},"annotation":{"meta":null,"sourceSpan":{"end":[112,41],"start":[112,15]}},"argument":{"abstraction":{"annotation":{"meta":{"metaType":"IsNewtype"},"sourceSpan":{"end":[112,32],"start":[112,24]}},"type":"Var","value":{"identifier":"ElemName","moduleName":["Halogen","VDom","Types"]}},"annotation":{"meta":null,"sourceSpan":{"end":[112,40],"start":[112,24]}},"argument":{"annotation":{"meta":null,"sourceSpan":{"end":[112,40],"start":[112,33]}},"type":"Literal","value":{"literalType":"StringLiteral","value":"mpath"}},"type":"App"},"type":"App"},"annotation":{"meta":null,"sourceSpan":{"end":[112,47],"start":[112,15]}},"argument":{"annotation":{"meta":null,"sourceSpan":{"end":[112,47],"start":[112,42]}},"type":"Var","value":{"identifier":"props","sourcePos":[112,1]}},"type":"App"},"annotation":{"meta":null,"sourceSpan":{"end":[112,50],"start":[112,15]}},"argument":{"annotation":{"meta":null,"sourceSpan":{"end":[112,50],"start":[112,48]}},"type":"Literal","value":{"literalType":"ArrayLiteral","value":[]}},"type":"App"},"type":"Abs"},"identifier":"mpath"},{"annotation":{"meta":null,"sourceSpan":{"end":[64,39],"start":[64,1]}},"bindType":"NonRec","expression":{"annotation":{"meta":null,"sourceSpan":{"end":[64,39],"start":[64,1]}},"argument":"props","body":{"abstraction":{"abstraction":{"abstraction":{"annotation":{"meta":null,"sourceSpan":{"end":[65,21],"start":[65,14]}},"type":"Var","value":{"identifier":"element","moduleName":["Halogen","Svg","Elements"]}},"annotation":{"meta":null,"sourceSpan":{"end":[65,39],"start":[65,14]}},"argument":{"abstraction":{"annotation":{"meta":{"metaType":"IsNewtype"},"sourceSpan":{"end":[65,31],"start":[65,23]}},"type":"Var","value":{"identifier":"ElemName","moduleName":["Halogen","VDom","Types"]}},"annotation":{"meta":null,"sourceSpan":{"end":[65,38],"start":[65,23]}},"argument":{"annotation":{"meta":null,"sourceSpan":{"end":[65,38],"start":[65,32]}},"type":"Literal","value":{"literalType":"StringLiteral","value":"path"}},"type":"App"},"type":"App"},"annotation":{"meta":null,"sourceSpan":{"end":[65,45],"start":[65,14]}},"argument":{"annotation":{"meta":null,"sourceSpan":{"end":[65,45],"start":[65,40]}},"type":"Var","value":{"identifier":"props","sourcePos":[65,1]}},"type":"App"},"annotation":{"meta":null,"sourceSpan":{"end":[65,48],"start":[65,14]}},"argument":{"annotation":{"meta":null,"sourceSpan":{"end":[65,48],"start":[65,46]}},"type":"Literal","value":{"literalType":"ArrayLiteral","value":[]}},"type":"App"},"type":"Abs"},"identifier":"path"},{"annotation":{"meta":null,"sourceSpan":{"end":[67,45],"start":[67,1]}},"bindType":"NonRec","expression":{"abstraction":{"annotation":{"meta":null,"sourceSpan":{"end":[68,18],"start":[68,11]}},"type":"Var","value":{"identifier":"element","moduleName":["Halogen","Svg","Elements"]}},"annotation":{"meta":null,"sourceSpan":{"end":[68,39],"start":[68,11]}},"argument":{"abstraction":{"annotation":{"meta":{"metaType":"IsNewtype"},"sourceSpan":{"end":[68,28],"start":[68,20]}},"type":"Var","value":{"identifier":"ElemName","moduleName":["Halogen","VDom","Types"]}},"annotation":{"meta":null,"sourceSpan":{"end":[68,38],"start":[68,20]}},"argument":{"annotation":{"meta":null,"sourceSpan":{"end":[68,38],"start":[68,29]}},"type":"Literal","value":{"literalType":"StringLiteral","value":"pattern"}},"type":"App"},"type":"App"},"identifier":"pattern"},{"annotation":{"meta":null,"sourceSpan":{"end":[76,45],"start":[76,1]}},"bindType":"NonRec","expression":{"annotation":{"meta":null,"sourceSpan":{"end":[76,45],"start":[76,1]}},"argument":"props","body":{"abstraction":{"abstraction":{"abstraction":{"annotation":{"meta":null,"sourceSpan":{"end":[77,24],"start":[77,17]}},"type":"Var","value":{"identifier":"element","moduleName":["Halogen","Svg","Elements"]}},"annotation":{"meta":null,"sourceSpan":{"end":[77,45],"start":[77,17]}},"argument":{"abstraction":{"annotation":{"meta":{"metaType":"IsNewtype"},"sourceSpan":{"end":[77,34],"start":[77,26]}},"type":"Var","value":{"identifier":"ElemName","moduleName":["Halogen","VDom","Types"]}},"annotation":{"meta":null,"sourceSpan":{"end":[77,44],"start":[77,26]}},"argument":{"annotation":{"meta":null,"sourceSpan":{"end":[77,44],"start":[77,35]}},"type":"Literal","value":{"literalType":"StringLiteral","value":"polygon"}},"type":"App"},"type":"App"},"annotation":{"meta":null,"sourceSpan":{"end":[77,51],"start":[77,17]}},"argument":{"annotation":{"meta":null,"sourceSpan":{"end":[77,51],"start":[77,46]}},"type":"Var","value":{"identifier":"props","sourcePos":[77,1]}},"type":"App"},"annotation":{"meta":null,"sourceSpan":{"end":[77,54],"start":[77,17]}},"argument":{"annotation":{"meta":null,"sourceSpan":{"end":[77,54],"start":[77,52]}},"type":"Literal","value":{"literalType":"ArrayLiteral","value":[]}},"type":"App"},"type":"Abs"},"identifier":"polygon"},{"annotation":{"meta":null,"sourceSpan":{"end":[73,47],"start":[73,1]}},"bindType":"NonRec","expression":{"annotation":{"meta":null,"sourceSpan":{"end":[73,47],"start":[73,1]}},"argument":"props","body":{"abstraction":{"abstraction":{"abstraction":{"annotation":{"meta":null,"sourceSpan":{"end":[74,25],"start":[74,18]}},"type":"Var","value":{"identifier":"element","moduleName":["Halogen","Svg","Elements"]}},"annotation":{"meta":null,"sourceSpan":{"end":[74,47],"start":[74,18]}},"argument":{"abstraction":{"annotation":{"meta":{"metaType":"IsNewtype"},"sourceSpan":{"end":[74,35],"start":[74,27]}},"type":"Var","value":{"identifier":"ElemName","moduleName":["Halogen","VDom","Types"]}},"annotation":{"meta":null,"sourceSpan":{"end":[74,46],"start":[74,27]}},"argument":{"annotation":{"meta":null,"sourceSpan":{"end":[74,46],"start":[74,36]}},"type":"Literal","value":{"literalType":"StringLiteral","value":"polyline"}},"type":"App"},"type":"App"},"annotation":{"meta":null,"sourceSpan":{"end":[74,53],"start":[74,18]}},"argument":{"annotation":{"meta":null,"sourceSpan":{"end":[74,53],"start":[74,48]}},"type":"Var","value":{"identifier":"props","sourcePos":[74,1]}},"type":"App"},"annotation":{"meta":null,"sourceSpan":{"end":[74,56],"start":[74,18]}},"argument":{"annotation":{"meta":null,"sourceSpan":{"end":[74,56],"start":[74,54]}},"type":"Literal","value":{"literalType":"ArrayLiteral","value":[]}},"type":"App"},"type":"Abs"},"identifier":"polyline"},{"annotation":{"meta":null,"sourceSpan":{"end":[61,39],"start":[61,1]}},"bindType":"NonRec","expression":{"annotation":{"meta":null,"sourceSpan":{"end":[61,39],"start":[61,1]}},"argument":"props","body":{"abstraction":{"abstraction":{"abstraction":{"annotation":{"meta":null,"sourceSpan":{"end":[62,21],"start":[62,14]}},"type":"Var","value":{"identifier":"element","moduleName":["Halogen","Svg","Elements"]}},"annotation":{"meta":null,"sourceSpan":{"end":[62,39],"start":[62,14]}},"argument":{"abstraction":{"annotation":{"meta":{"metaType":"IsNewtype"},"sourceSpan":{"end":[62,31],"start":[62,23]}},"type":"Var","value":{"identifier":"ElemName","moduleName":["Halogen","VDom","Types"]}},"annotation":{"meta":null,"sourceSpan":{"end":[62,38],"start":[62,23]}},"argument":{"annotation":{"meta":null,"sourceSpan":{"end":[62,38],"start":[62,32]}},"type":"Literal","value":{"literalType":"StringLiteral","value":"rect"}},"type":"App"},"type":"App"},"annotation":{"meta":null,"sourceSpan":{"end":[62,45],"start":[62,14]}},"argument":{"annotation":{"meta":null,"sourceSpan":{"end":[62,45],"start":[62,40]}},"type":"Var","value":{"identifier":"props","sourcePos":[62,1]}},"type":"App"},"annotation":{"meta":null,"sourceSpan":{"end":[62,48],"start":[62,14]}},"argument":{"annotation":{"meta":null,"sourceSpan":{"end":[62,48],"start":[62,46]}},"type":"Literal","value":{"literalType":"ArrayLiteral","value":[]}},"type":"App"},"type":"Abs"},"identifier":"rect"},{"annotation":{"meta":null,"sourceSpan":{"end":[46,37],"start":[46,1]}},"bindType":"NonRec","expression":{"abstraction":{"annotation":{"meta":null,"sourceSpan":{"end":[47,14],"start":[47,7]}},"type":"Var","value":{"identifier":"element","moduleName":["Halogen","Svg","Elements"]}},"annotation":{"meta":null,"sourceSpan":{"end":[47,31],"start":[47,7]}},"argument":{"abstraction":{"annotation":{"meta":{"metaType":"IsNewtype"},"sourceSpan":{"end":[47,25],"start":[47,17]}},"type":"Var","value":{"identifier":"ElemName","moduleName":["Halogen","VDom","Types"]}},"annotation":{"meta":null,"sourceSpan":{"end":[47,31],"start":[47,17]}},"argument":{"annotation":{"meta":null,"sourceSpan":{"end":[47,31],"start":[47,26]}},"type":"Literal","value":{"literalType":"StringLiteral","value":"svg"}},"type":"App"},"type":"App"},"identifier":"svg"},{"annotation":{"meta":null,"sourceSpan":{"end":[79,39],"start":[79,1]}},"bindType":"NonRec","expression":{"abstraction":{"annotation":{"meta":null,"sourceSpan":{"end":[80,15],"start":[80,8]}},"type":"Var","value":{"identifier":"element","moduleName":["Halogen","Svg","Elements"]}},"annotation":{"meta":null,"sourceSpan":{"end":[80,33],"start":[80,8]}},"argument":{"abstraction":{"annotation":{"meta":{"metaType":"IsNewtype"},"sourceSpan":{"end":[80,25],"start":[80,17]}},"type":"Var","value":{"identifier":"ElemName","moduleName":["Halogen","VDom","Types"]}},"annotation":{"meta":null,"sourceSpan":{"end":[80,32],"start":[80,17]}},"argument":{"annotation":{"meta":null,"sourceSpan":{"end":[80,32],"start":[80,26]}},"type":"Literal","value":{"literalType":"StringLiteral","value":"text"}},"type":"App"},"type":"App"},"identifier":"text"},{"annotation":{"meta":null,"sourceSpan":{"end":[116,41],"start":[116,1]}},"bindType":"NonRec","expression":{"abstraction":{"annotation":{"meta":null,"sourceSpan":{"end":[117,16],"start":[117,9]}},"type":"Var","value":{"identifier":"element","moduleName":["Halogen","Svg","Elements"]}},"annotation":{"meta":null,"sourceSpan":{"end":[117,35],"start":[117,9]}},"argument":{"abstraction":{"annotation":{"meta":{"metaType":"IsNewtype"},"sourceSpan":{"end":[117,26],"start":[117,18]}},"type":"Var","value":{"identifier":"ElemName","moduleName":["Halogen","VDom","Types"]}},"annotation":{"meta":null,"sourceSpan":{"end":[117,34],"start":[117,18]}},"argument":{"annotation":{"meta":null,"sourceSpan":{"end":[117,34],"start":[117,27]}},"type":"Literal","value":{"literalType":"StringLiteral","value":"title"}},"type":"App"},"type":"App"},"identifier":"title"},{"annotation":{"meta":null,"sourceSpan":{"end":[82,37],"start":[82,1]}},"bindType":"NonRec","expression":{"annotation":{"meta":null,"sourceSpan":{"end":[82,37],"start":[82,1]}},"argument":"props","body":{"abstraction":{"abstraction":{"abstraction":{"annotation":{"meta":null,"sourceSpan":{"end":[83,20],"start":[83,13]}},"type":"Var","value":{"identifier":"element","moduleName":["Halogen","Svg","Elements"]}},"annotation":{"meta":null,"sourceSpan":{"end":[83,37],"start":[83,13]}},"argument":{"abstraction":{"annotation":{"meta":{"metaType":"IsNewtype"},"sourceSpan":{"end":[83,30],"start":[83,22]}},"type":"Var","value":{"identifier":"ElemName","moduleName":["Halogen","VDom","Types"]}},"annotation":{"meta":null,"sourceSpan":{"end":[83,36],"start":[83,22]}},"argument":{"annotation":{"meta":null,"sourceSpan":{"end":[83,36],"start":[83,31]}},"type":"Literal","value":{"literalType":"StringLiteral","value":"use"}},"type":"App"},"type":"App"},"annotation":{"meta":null,"sourceSpan":{"end":[83,43],"start":[83,13]}},"argument":{"annotation":{"meta":null,"sourceSpan":{"end":[83,43],"start":[83,38]}},"type":"Var","value":{"identifier":"props","sourcePos":[83,1]}},"type":"App"},"annotation":{"meta":null,"sourceSpan":{"end":[83,46],"start":[83,13]}},"argument":{"annotation":{"meta":null,"sourceSpan":{"end":[83,46],"start":[83,44]}},"type":"Literal","value":{"literalType":"ArrayLiteral","value":[]}},"type":"App"},"type":"Abs"},"identifier":"use"},{"annotation":{"meta":null,"sourceSpan":{"end":[88,36],"start":[88,1]}},"bindType":"NonRec","expression":{"abstraction":{"annotation":{"meta":null,"sourceSpan":{"end":[89,15],"start":[89,8]}},"type":"Var","value":{"identifier":"element","moduleName":["Halogen","Svg","Elements"]}},"annotation":{"meta":null,"sourceSpan":{"end":[89,33],"start":[89,8]}},"argument":{"abstraction":{"annotation":{"meta":{"metaType":"IsNewtype"},"sourceSpan":{"end":[89,26],"start":[89,18]}},"type":"Var","value":{"identifier":"ElemName","moduleName":["Halogen","VDom","Types"]}},"annotation":{"meta":null,"sourceSpan":{"end":[89,33],"start":[89,18]}},"argument":{"annotation":{"meta":null,"sourceSpan":{"end":[89,33],"start":[89,27]}},"type":"Literal","value":{"literalType":"StringLiteral","value":"defs"}},"type":"App"},"type":"App"},"identifier":"defs"},{"annotation":{"meta":null,"sourceSpan":{"end":[106,47],"start":[106,1]}},"bindType":"NonRec","expression":{"abstraction":{"annotation":{"meta":null,"sourceSpan":{"end":[107,21],"start":[107,14]}},"type":"Var","value":{"identifier":"element","moduleName":["Halogen","Svg","Elements"]}},"annotation":{"meta":null,"sourceSpan":{"end":[107,41],"start":[107,14]}},"argument":{"abstraction":{"annotation":{"meta":{"metaType":"IsNewtype"},"sourceSpan":{"end":[107,31],"start":[107,23]}},"type":"Var","value":{"identifier":"ElemName","moduleName":["Halogen","VDom","Types"]}},"annotation":{"meta":null,"sourceSpan":{"end":[107,40],"start":[107,23]}},"argument":{"annotation":{"meta":null,"sourceSpan":{"end":[107,40],"start":[107,32]}},"type":"Literal","value":{"literalType":"StringLiteral","value":"circle"}},"type":"App"},"type":"App"},"identifier":"circleNode"},{"annotation":{"meta":null,"sourceSpan":{"end":[52,43],"start":[52,1]}},"bindType":"NonRec","expression":{"annotation":{"meta":null,"sourceSpan":{"end":[52,43],"start":[52,1]}},"argument":"props","body":{"abstraction":{"abstraction":{"abstraction":{"annotation":{"meta":null,"sourceSpan":{"end":[53,23],"start":[53,16]}},"type":"Var","value":{"identifier":"element","moduleName":["Halogen","Svg","Elements"]}},"annotation":{"meta":null,"sourceSpan":{"end":[53,43],"start":[53,16]}},"argument":{"abstraction":{"annotation":{"meta":{"metaType":"IsNewtype"},"sourceSpan":{"end":[53,33],"start":[53,25]}},"type":"Var","value":{"identifier":"ElemName","moduleName":["Halogen","VDom","Types"]}},"annotation":{"meta":null,"sourceSpan":{"end":[53,42],"start":[53,25]}},"argument":{"annotation":{"meta":null,"sourceSpan":{"end":[53,42],"start":[53,34]}},"type":"Literal","value":{"literalType":"StringLiteral","value":"circle"}},"type":"App"},"type":"App"},"annotation":{"meta":null,"sourceSpan":{"end":[53,49],"start":[53,16]}},"argument":{"annotation":{"meta":null,"sourceSpan":{"end":[53,49],"start":[53,44]}},"type":"Var","value":{"identifier":"props","sourcePos":[53,1]}},"type":"App"},"annotation":{"meta":null,"sourceSpan":{"end":[53,52],"start":[53,16]}},"argument":{"annotation":{"meta":null,"sourceSpan":{"end":[53,52],"start":[53,50]}},"type":"Literal","value":{"literalType":"ArrayLiteral","value":[]}},"type":"App"},"type":"Abs"},"identifier":"circle"},{"annotation":{"meta":null,"sourceSpan":{"end":[103,57],"start":[103,1]}},"bindType":"NonRec","expression":{"abstraction":{"annotation":{"meta":null,"sourceSpan":{"end":[104,24],"start":[104,17]}},"type":"Var","value":{"identifier":"element","moduleName":["Halogen","Svg","Elements"]}},"annotation":{"meta":null,"sourceSpan":{"end":[104,51],"start":[104,17]}},"argument":{"abstraction":{"annotation":{"meta":{"metaType":"IsNewtype"},"sourceSpan":{"end":[104,34],"start":[104,26]}},"type":"Var","value":{"identifier":"ElemName","moduleName":["Halogen","VDom","Types"]}},"annotation":{"meta":null,"sourceSpan":{"end":[104,50],"start":[104,26]}},"argument":{"annotation":{"meta":null,"sourceSpan":{"end":[104,50],"start":[104,35]}},"type":"Literal","value":{"literalType":"StringLiteral","value":"animateMotion"}},"type":"App"},"type":"App"},"identifier":"animateMotion"},{"annotation":{"meta":null,"sourceSpan":{"end":[99,45],"start":[99,1]}},"bindType":"NonRec","expression":{"annotation":{"meta":null,"sourceSpan":{"end":[99,45],"start":[99,1]}},"argument":"props","body":{"abstraction":{"abstraction":{"abstraction":{"annotation":{"meta":null,"sourceSpan":{"end":[100,24],"start":[100,17]}},"type":"Var","value":{"identifier":"element","moduleName":["Halogen","Svg","Elements"]}},"annotation":{"meta":null,"sourceSpan":{"end":[100,45],"start":[100,17]}},"argument":{"abstraction":{"annotation":{"meta":{"metaType":"IsNewtype"},"sourceSpan":{"end":[100,34],"start":[100,26]}},"type":"Var","value":{"identifier":"ElemName","moduleName":["Halogen","VDom","Types"]}},"annotation":{"meta":null,"sourceSpan":{"end":[100,44],"start":[100,26]}},"argument":{"annotation":{"meta":null,"sourceSpan":{"end":[100,44],"start":[100,35]}},"type":"Literal","value":{"literalType":"StringLiteral","value":"animate"}},"type":"App"},"type":"App"},"annotation":{"meta":null,"sourceSpan":{"end":[100,51],"start":[100,17]}},"argument":{"annotation":{"meta":null,"sourceSpan":{"end":[100,51],"start":[100,46]}},"type":"Var","value":{"identifier":"props","sourcePos":[100,1]}},"type":"App"},"annotation":{"meta":null,"sourceSpan":{"end":[100,54],"start":[100,17]}},"argument":{"annotation":{"meta":null,"sourceSpan":{"end":[100,54],"start":[100,52]}},"type":"Literal","value":{"literalType":"ArrayLiteral","value":[]}},"type":"App"},"type":"Abs"},"identifier":"animate"}],"exports":["element","svg","g","circle","image","ellipse","rect","path","pattern","line","polyline","polygon","text","foreignObject","defs","mask","marker","animate","animateMotion","circleNode","mpath","title","use"],"foreign":[],"imports":[{"annotation":{"meta":null,"sourceSpan":{"end":[117,35],"start":[6,1]}},"moduleName":["Data","Function"]},{"annotation":{"meta":null,"sourceSpan":{"end":[35,61],"start":[35,1]}},"moduleName":["Halogen","HTML","Core"]},{"annotation":{"meta":null,"sourceSpan":{"end":[117,35],"start":[6,1]}},"moduleName":["Halogen","HTML","Elements"]},{"annotation":{"meta":null,"sourceSpan":{"end":[37,39],"start":[37,1]}},"moduleName":["Halogen","HTML","Properties"]},{"annotation":{"meta":null,"sourceSpan":{"end":[117,35],"start":[6,1]}},"moduleName":["Halogen","Svg","Elements"]},{"annotation":{"meta":null,"sourceSpan":{"end":[38,32],"start":[38,1]}},"moduleName":["Halogen","Svg","Indexed"]},{"annotation":{"meta":null,"sourceSpan":{"end":[117,35],"start":[6,1]}},"moduleName":["Halogen","VDom","Types"]},{"annotation":{"meta":null,"sourceSpan":{"end":[34,15],"start":[34,1]}},"moduleName":["Prelude"]},{"annotation":{"meta":null,"sourceSpan":{"end":[117,35],"start":[6,1]}},"moduleName":["Prim"]}],"moduleName":["Halogen","Svg","Elements"],"modulePath":".spago/p/halogen-svg-elems-8.0.0/src/Halogen/Svg/Elements.purs","reExports":{},"sourceSpan":{"end":[117,35],"start":[6,1]}}